__init__.py
database/__init__.py
database/model.py
database/read_mixin.py
database/tables_mixin.py
database/write_mixin.py
geometry/__init__.py
geometry/plane.py
geometry/vector_3d.py
objects/__init__.py
objects/element.py
objects/load.py
objects/properties.py
plot/__init__.py
plot/plot.py
scpyce-0.1.3.dist-info/LICENSE
scpyce-0.1.3.dist-info/METADATA
scpyce-0.1.3.dist-info/WHEEL
scpyce-0.1.3.dist-info/top_level.txt
scpyce-0.1.3.dist-info/RECORD
