Metadata-Version: 2.2
Name: scpyce
Version: 0.1.3
Summary: SQL based library for building and visualising finite element models.
Author-email: Nicolo Bencini <nicbencini@gmail.com>
Project-URL: Homepage, https://github.com/nicbencini/scpyce
Project-URL: Issues, https://github.com/nicbencini/scpyce/issues
Classifier: Programming Language :: Python :: 3
Classifier: License :: OSI Approved :: MIT License
Classifier: Operating System :: OS Independent
Requires-Python: >=3.8
License-File: LICENSE
Requires-Dist: numpy
Requires-Dist: sqlite3
Requires-Dist: matplotlib
Requires-Dist: PyQt6
